README.md
setup.py
frcrules/__init__.py
frcrules/api_client.py
frcrules/configuration.py
frcrules/exceptions.py
frcrules/rest.py
frcrules.egg-info/PKG-INFO
frcrules.egg-info/SOURCES.txt
frcrules.egg-info/dependency_links.txt
frcrules.egg-info/requires.txt
frcrules.egg-info/top_level.txt
frcrules/api/__init__.py
frcrules/api/get_rule_api.py
frcrules/api/get_rule_list_api.py
frcrules/models/__init__.py
test/__init__.py
test/test_get_rule_api.py
test/test_get_rule_list_api.py