Metadata-Version: 1.0
Name: frcrules
Version: 1.0.1
Summary: Ruler API
Home-page: UNKNOWN
Author: UNKNOWN
Author-email: UNKNOWN
License: UNKNOWN
Keywords: OpenAPI,OpenAPI-Generator,Ruler API
Platform: UNKNOWN
